README.rst
setup.py
pytest_ochrus/__init__.py
pytest_ochrus/plugin.py
pytest_ochrus.egg-info/PKG-INFO
pytest_ochrus.egg-info/SOURCES.txt
pytest_ochrus.egg-info/dependency_links.txt
pytest_ochrus.egg-info/entry_points.txt
pytest_ochrus.egg-info/not-zip-safe
pytest_ochrus.egg-info/requires.txt
pytest_ochrus.egg-info/top_level.txt