Metadata-Version: 1.1
Name: pytest-ochrus
Version: 0.0.6
Summary: pytest results data-base and HTML reporter
Home-page: https://github.com/ochrus/pytest-ochrus
Author: Roni Eliezer
Author-email: roniezr@gmail.com
License: MIT
Keywords: pytest results data-base and HTML reporter
Platform: UNKNOWN
Classifier: Development Status :: 4 - Beta
Classifier: Programming Language :: Python :: 2.7
Classifier: Intended Audience :: Developers
Classifier: Framework :: Pytest
